{
  "generatedAtUtc": "2026-06-27T14:03:13.6552186Z",
  "results": [
    {
      "status": "Passed",
      "severity": "info",
      "message": "YAML parsed with PyYAML 6.0.2.",
      "path": ".github/dependabot.yml",
      "data": null
    },
    {
      "status": "Passed",
      "severity": "info",
      "message": "YAML parsed with PyYAML 6.0.2.",
      "path": ".github/ISSUE_TEMPLATE/bug_report.yml",
      "data": null
    },
    {
      "status": "Passed",
      "severity": "info",
      "message": "YAML parsed with PyYAML 6.0.2.",
      "path": ".github/ISSUE_TEMPLATE/config.yml",
      "data": null
    },
    {
      "status": "Passed",
      "severity": "info",
      "message": "YAML parsed with PyYAML 6.0.2.",
      "path": ".github/ISSUE_TEMPLATE/feature_request.yml",
      "data": null
    },
    {
      "status": "Passed",
      "severity": "info",
      "message": "YAML parsed with PyYAML 6.0.2.",
      "path": ".github/ISSUE_TEMPLATE/governance_exception.yml",
      "data": null
    },
    {
      "status": "Passed",
      "severity": "info",
      "message": "YAML parsed with PyYAML 6.0.2.",
      "path": ".github/workflows/governance-ci-reusable.yml",
      "data": null
    },
    {
      "status": "Passed",
      "severity": "info",
      "message": "YAML parsed with PyYAML 6.0.2.",
      "path": ".github/workflows/governance-ci.yml",
      "data": null
    },
    {
      "status": "Passed",
      "severity": "info",
      "message": "YAML parsed with PyYAML 6.0.2.",
      "path": "examples/combined-script-runner-project/.github/workflows/governance.yml",
      "data": null
    },
    {
      "status": "Passed",
      "severity": "info",
      "message": "YAML parsed with PyYAML 6.0.2.",
      "path": "examples/database-project/.github/workflows/governance.yml",
      "data": null
    },
    {
      "status": "Passed",
      "severity": "info",
      "message": "YAML parsed with PyYAML 6.0.2.",
      "path": "examples/dotnet-project/.github/workflows/governance.yml",
      "data": null
    },
    {
      "status": "Passed",
      "severity": "info",
      "message": "YAML parsed with PyYAML 6.0.2.",
      "path": "examples/infrastructure-project/.github/workflows/governance.yml",
      "data": null
    },
    {
      "status": "Passed",
      "severity": "info",
      "message": "YAML parsed with PyYAML 6.0.2.",
      "path": "examples/integration-project/.github/workflows/governance.yml",
      "data": null
    },
    {
      "status": "Passed",
      "severity": "info",
      "message": "YAML parsed with PyYAML 6.0.2.",
      "path": "examples/powershell-project/.github/workflows/governance.yml",
      "data": null
    },
    {
      "status": "Passed",
      "severity": "info",
      "message": "YAML parsed with PyYAML 6.0.2.",
      "path": "examples/web-project/.github/workflows/governance.yml",
      "data": null
    },
    {
      "status": "Passed",
      "severity": "info",
      "message": "YAML parsed with PyYAML 6.0.2.",
      "path": "examples/worker-service-project/.github/workflows/governance.yml",
      "data": null
    },
    {
      "status": "Passed",
      "severity": "info",
      "message": "YAML parsed with PyYAML 6.0.2.",
      "path": "templates/issues/bug_report.yml",
      "data": null
    },
    {
      "status": "Passed",
      "severity": "info",
      "message": "YAML parsed with PyYAML 6.0.2.",
      "path": "templates/issues/config.yml",
      "data": null
    },
    {
      "status": "Passed",
      "severity": "info",
      "message": "YAML parsed with PyYAML 6.0.2.",
      "path": "templates/issues/feature_request.yml",
      "data": null
    },
    {
      "status": "Passed",
      "severity": "info",
      "message": "YAML parsed with PyYAML 6.0.2.",
      "path": "templates/issues/governance_exception.yml",
      "data": null
    },
    {
      "status": "Passed",
      "severity": "info",
      "message": "YAML parsed with PyYAML 6.0.2.",
      "path": "workflows/database-ci.yml",
      "data": null
    },
    {
      "status": "Passed",
      "severity": "info",
      "message": "YAML parsed with PyYAML 6.0.2.",
      "path": "workflows/dotnet-ci.yml",
      "data": null
    },
    {
      "status": "Passed",
      "severity": "info",
      "message": "YAML parsed with PyYAML 6.0.2.",
      "path": "workflows/governance-ci.yml",
      "data": null
    },
    {
      "status": "Passed",
      "severity": "info",
      "message": "YAML parsed with PyYAML 6.0.2.",
      "path": "workflows/powershell-ci.yml",
      "data": null
    },
    {
      "status": "Passed",
      "severity": "info",
      "message": "YAML parsed with PyYAML 6.0.2.",
      "path": "workflows/web-ci.yml",
      "data": null
    }
  ],
  "failed": 0,
  "warnings": 0,
  "blocked": 0,
  "notRun": 0
}
